deep_research_anything/__init__.py
deep_research_anything/agent/__init__.py
deep_research_anything/agent/agent.py
deep_research_anything/agent/agents/__init__.py
deep_research_anything/agent/agents/end/__init__.py
deep_research_anything/agent/agents/end/_cross_validation.py
deep_research_anything/agent/agents/end/_essay.py
deep_research_anything/agent/agents/end/ending.py
deep_research_anything/agent/agents/end/models.py
deep_research_anything/agent/agents/search/__init__.py
deep_research_anything/agent/agents/search/_firecrawl.py
deep_research_anything/agent/agents/search/models.py
deep_research_anything/agent/agents/search/search.py
deep_research_anything/agent/call.py
deep_research_anything/agent/derived_parameters.py
deep_research_anything/agent/parameter.py
deep_research_anything/agent/registry.py
deep_research_anything/deep_research.py
deep_research_anything/llms.py
deep_research_anything/models/base.py
deep_research_anything/models/default.py
deep_research_anything/models/event.py
deep_research_anything/tool/__init__.py
deep_research_anything/tool/tool.py
deep_research_anything/tool/tool_parameter.py
deep_research_anything/tool/tools/__init__.py
deep_research_anything/tool/tools/coding/__init__.py
deep_research_anything/tool/tools/coding/coding.py
deep_research_anything/tool/tools/coding/models.py
deep_research_anything/tool/tools/coding/utils.py
deep_research_anything/tool/utils.py
deep_research_anything-0.1.0.dist-info/LICENSE
deep_research_anything-0.1.0.dist-info/METADATA
deep_research_anything-0.1.0.dist-info/WHEEL
deep_research_anything-0.1.0.dist-info/RECORD
