Metadata-Version: 2.3
Name: deep-research-anything
Version: 0.1.0
Summary: 
Author: Hao Sun
Author-email: author@example.com
Requires-Python: >=3.11,<4.0
Classifier: Programming Language :: Python :: 3
Classifier: Programming Language :: Python :: 3.11
Classifier: Programming Language :: Python :: 3.12
Classifier: Programming Language :: Python :: 3.13
Requires-Dist: firecrawl-py (>=1.12.0,<2.0.0)
Requires-Dist: litellm (>=1.63.3,<2.0.0)
Requires-Dist: llama-index (>=0.12.23,<0.13.0)
Requires-Dist: pydantic (>=2.10.6,<3.0.0)
Requires-Dist: streamlit (>=1.43.1,<2.0.0)
